{"commentText": "Class for reporting problems when the primary key constraint is being broken.", "tags": [{"_class": "SeeTag", "name": "@see", "kind": "@see", "text": "io.realm.annotations.PrimaryKey", "inlineTags": [{"_class": "Tag", "name": "Text", "kind": "Text", "text": "io.realm.annotations.PrimaryKey"}], "firstSentenceTags": [{"_class": "Tag", "name": "Text", "kind": "Text", "text": "io.realm.annotations.PrimaryKey"}], "label": "", "referencedClassName": "io.realm.annotations.PrimaryKey"}], "seeTags": [{"_class": "SeeTag", "name": "@see", "kind": "@see", "text": "io.realm.annotations.PrimaryKey", "inlineTags": [{"_class": "Tag", "name": "Text", "kind": "Text", "text": "io.realm.annotations.PrimaryKey"}], "firstSentenceTags": [{"_class": "Tag", "name": "Text", "kind": "Text", "text": "io.realm.annotations.PrimaryKey"}], "label": "", "referencedClassName": "io.realm.annotations.PrimaryKey"}], "inlineTags": [{"_class": "Tag", "name": "Text", "kind": "Text", "text": "Class for reporting problems when the primary key constraint is being broken.", "inlineTags": [{"_class": "Tag", "name": "Text", "kind": "Text", "text": "Class for reporting problems when the primary key constraint is being broken."}], "firstSentenceTags": [{"_class": "Tag", "name": "Text", "kind": "Text", "text": "Class for reporting problems when the primary key constraint is being broken."}]}], "firstSentenceTags": [{"_class": "Tag", "name": "Text", "kind": "Text", "text": "Class for reporting problems when the primary key constraint is being broken.", "inlineTags": [{"_class": "Tag", "name": "Text", "kind": "Text", "text": "Class for reporting problems when the primary key constraint is being broken."}], "firstSentenceTags": [{"_class": "Tag", "name": "Text", "kind": "Text", "text": "Class for reporting problems when the primary key constraint is being broken."}]}], "name": "RealmPrimaryKeyConstraintException", "isField": false, "isEnumConstant": false, "isConstructor": false, "isMethod": false, "isAnnotationTypeElement": false, "isInterface": false, "isException": true, "isError": false, "isEnum": false, "isAnnotationType": false, "isOrdinaryClass": false, "isClass": true, "isIncluded": true, "position": {"line": 28, "column": 14, "file": "realm/realm-library/src/main/java/io/realm/exceptions/RealmPrimaryKeyConstraintException.java"}, "_class": "ParsedClassDoc", "containingPackage": {"_class": "PackageDoc", "name": "io.realm.exceptions"}, "qualifiedName": "io.realm.exceptions.RealmPrimaryKeyConstraintException", "modifierSpecifier": 17, "modifiers": "public final", "annotations": [{"annotationType": {"_class": "ClassDoc", "asString": "io.realm.internal.Keep", "typeName": "Keep", "qualifiedTypeName": "io.realm.internal.Keep", "simpleTypeName": "Keep", "dimension": "", "isPrimitive": false, "isClass": true, "isAnnotationType": true, "modifiers": "public interface"}, "elementValues": [], "isSynthesized": false}], "isPublic": true, "isProtected": false, "isPrivate": false, "isPackagePrivate": false, "isStatic": false, "isFinal": true, "asString": "io.realm.exceptions.RealmPrimaryKeyConstraintException", "typeName": "RealmPrimaryKeyConstraintException", "qualifiedTypeName": "io.realm.exceptions.RealmPrimaryKeyConstraintException", "simpleTypeName": "RealmPrimaryKeyConstraintException", "dimension": "", "isPrimitive": false, "isAbstract": false, "isSerializable": true, "isExternalizable": false, "serializationMethods": [], "serializableFields": [], "definesSerializableFields": false, "superclasses": [{"_class": "ClassDoc", "asString": "java.lang.RuntimeException", "typeName": "RuntimeException", "qualifiedTypeName": "java.lang.RuntimeException", "simpleTypeName": "RuntimeException", "dimension": "", "isPrimitive": false, "isClass": true, "isAnnotationType": false}, {"_class": "ClassDoc", "asString": "java.lang.Exception", "typeName": "Exception", "qualifiedTypeName": "java.lang.Exception", "simpleTypeName": "Exception", "dimension": "", "isPrimitive": false, "isClass": true, "isAnnotationType": false}, {"_class": "ClassDoc", "asString": "java.lang.Throwable", "typeName": "Throwable", "qualifiedTypeName": "java.lang.Throwable", "simpleTypeName": "Throwable", "dimension": "", "isPrimitive": false, "isClass": true, "isAnnotationType": false}, {"_class": "ClassDoc", "asString": "java.lang.Object", "typeName": "Object", "qualifiedTypeName": "java.lang.Object", "simpleTypeName": "Object", "dimension": "", "isPrimitive": false, "isClass": true, "isAnnotationType": false}], "inheritedMethods": {"java.lang.RuntimeException": [], "java.lang.Exception": [], "java.lang.Throwable": ["getMessage", "getLocalizedMessage", "getCause", "initCause", "toString", "printStackTrace", "printStackTrace", "printStackTrace", "fillInStackTrace", "getStackTrace", "setStackTrace", "addSuppressed", "getSuppressed"], "java.lang.Object": ["getClass", "hashCode", "equals", "clone", "toString", "notify", "notifyAll", "wait", "wait", "wait", "finalize"]}, "interfaceTypes": [], "typeParameters": [], "typeParamTags": [], "fields": [], "enumConstants": [], "methods": [], "constructors": [{"commentText": "", "tags": [], "seeTags": [], "inlineTags": [], "firstSentenceTags": [], "name": "RealmPrimaryKeyConstraintException", "isField": false, "isEnumConstant": false, "isConstructor": true, "isMethod": false, "isAnnotationTypeElement": false, "isInterface": false, "isException": false, "isError": false, "isEnum": false, "isAnnotationType": false, "isOrdinaryClass": false, "isClass": false, "isIncluded": true, "position": {"line": 29, "column": 12, "file": "realm/realm-library/src/main/java/io/realm/exceptions/RealmPrimaryKeyConstraintException.java"}, "_class": "ExecutableMemberDoc", "containingClass": {"_class": "ClassDoc", "asString": "io.realm.exceptions.RealmPrimaryKeyConstraintException", "typeName": "RealmPrimaryKeyConstraintException", "qualifiedTypeName": "io.realm.exceptions.RealmPrimaryKeyConstraintException", "simpleTypeName": "RealmPrimaryKeyConstraintException", "dimension": "", "isPrimitive": false, "isClass": true, "isAnnotationType": false, "modifiers": "public final"}, "containingPackage": {"_class": "PackageDoc", "name": "io.realm.exceptions"}, "qualifiedName": "io.realm.exceptions.RealmPrimaryKeyConstraintException", "modifierSpecifier": 1, "modifiers": "public", "annotations": [], "isPublic": true, "isProtected": false, "isPrivate": false, "isPackagePrivate": false, "isStatic": false, "isFinal": false, "isSynthetic": false, "thrownExceptionTypes": [], "isNative": false, "isSynchronized": false, "isVarArgs": false, "parameters": [{"type": {"_class": "ClassDoc", "asString": "java.lang.String", "typeName": "String", "qualifiedTypeName": "java.lang.String", "simpleTypeName": "String", "dimension": "", "isPrimitive": false, "isClass": true, "isAnnotationType": false}, "name": "message", "typeName": "String", "asString": "String message", "annotations": []}], "throwsTags": [], "paramTags": [], "typeParamTags": [], "signature": "(java.lang.String)", "flatSignature": "(String)", "typeParameters": []}], "innerClasses": []}